argufy/__init__.py
argufy/argument.py
argufy/exceptions.py
argufy/formatter.py
argufy/parser.py
argufy/py.typed
argufy-0.1.2b4.dist-info/METADATA
argufy-0.1.2b4.dist-info/WHEEL
argufy-0.1.2b4.dist-info/licenses/LICENSE
argufy-0.1.2b4.dist-info/RECORD
