Metadata-Version: 2.3
Name: argufy
Version: 0.1.2b4
Summary: Inspection based parser based on argparse.
Project-URL: homepage, https://github.com/kuwv/python-argufy
Project-URL: repository, https://github.com/kuwv/python-argufy
Project-URL: documentation, https://kuwv.github.io/python-argufy/
Author-email: "Jesse P. Johnson" <jpj6652@gmail.com>
Maintainer-email: "Jesse P. Johnson" <jpj6652@gmail.com>
License:                                  Apache License
License-File: LICENSE
Keywords: parser
Classifier: Development Status :: 4 - Beta
Classifier: Intended Audience :: Developers
Classifier: License :: OSI Approved :: Apache Software License
Classifier: Programming Language :: Python
Classifier: Programming Language :: Python :: 3
Classifier: Programming Language :: Python :: 3.6
Classifier: Programming Language :: Python :: 3.7
Classifier: Programming Language :: Python :: 3.8
Classifier: Programming Language :: Python :: 3.9
Classifier: Programming Language :: Python :: 3.10
Classifier: Programming Language :: Python :: 3.11
Classifier: Programming Language :: Python :: 3.12
Classifier: Topic :: Software Development :: Libraries
Requires-Python: >=3.6.2
Requires-Dist: colorama>=0.4.4
Requires-Dist: docstring-parser>=0.7.2
Provides-Extra: build
Requires-Dist: build; extra == 'build'
Requires-Dist: proman-versioning>=0.5.0-alpha.2; extra == 'build'
Requires-Dist: twine; extra == 'build'
Provides-Extra: dev
Requires-Dist: bandit>=1.6.2; extra == 'dev'
Requires-Dist: black==22.3.0; extra == 'dev'
Requires-Dist: flake8>=3.8.3; extra == 'dev'
Requires-Dist: isort>=5.10.1; extra == 'dev'
Requires-Dist: mypy>=1; extra == 'dev'
Requires-Dist: pylint>=3; extra == 'dev'
Requires-Dist: pytest-cov>=2.10.0; extra == 'dev'
Requires-Dist: pytest>=6.2.5; extra == 'dev'
Requires-Dist: safety>=1.9.0; extra == 'dev'
Requires-Dist: tox>=3.25.0; extra == 'dev'
Provides-Extra: docs
Requires-Dist: docstr-coverage>=1.2.0; extra == 'docs'
Requires-Dist: mkdocs-material>=7.2.0; extra == 'docs'
Requires-Dist: mkdocs>=1.2.2; extra == 'docs'
Requires-Dist: mkdocstrings[python]>=0.16.2; extra == 'docs'
Requires-Dist: pydocstyle[toml]>=6.1.1; extra == 'docs'
